{
  "LH": "Lufthansa",
  "LX": "SWISS",
  "AZ": "ITA Airways",
  "KL": "KLM Royal Dutch Airlines",
  "AF": "Air France",
  "IB": "Iberia",
  "LA": "LATAM Airlines",
  "AC": "Air Canada",
  "UX": "Air Europa",
  "AA": "American Airlines",
  "UA": "United Airlines",
  "DL": "Delta Air Lines",
  "AR": "Aerolíneas Argentinas",
  "TK": "Turkish Airlines",
  "BA": "British Airways",
  "QR": "Qatar Airways",
  "EK": "Emirates",
  "AV": "Avianca",
  "CM": "Copa Airlines",
  "AM": "Aeroméxico",
  "NH": "ANA All Nippon Airways",
  "JL": "Japan Airlines",
  "EY": "Etihad Airways",
  "QF": "Qantas",
  "NZ": "Air New Zealand",
  "VS": "Virgin Atlantic",
  "IB": "Iberia",
  "SK": "Scandinavian Airlines",
  "SN": "Brussels Airlines"
}
